lemming/__init__.py
lemming/__main__.py
lemming/config.py
lemming/py.typed
python_lemming-0.7.0.dist-info/LICENSE
python_lemming-0.7.0.dist-info/METADATA
python_lemming-0.7.0.dist-info/WHEEL
python_lemming-0.7.0.dist-info/entry_points.txt
python_lemming-0.7.0.dist-info/top_level.txt
python_lemming-0.7.0.dist-info/RECORD
