Metadata-Version: 2.1
Name: python_lemming
Version: 0.7.0
Summary: Lemming is a tool for formatting and linting code.
Author-email: Koviubi56 <koviubi56@duck.com>
License: GPL-3.0-or-later
Project-URL: Homepage, https://github.com/koviubi56/lemming
Keywords: lemming,format,formatter,lint,linting,linter
Classifier: Development Status :: 4 - Beta
Classifier: Intended Audience :: Developers
Classifier: License :: OSI Approved :: GNU General Public License v3 or later (GPLv3+)
Classifier: Natural Language :: English
Classifier: Operating System :: OS Independent
Classifier: Programming Language :: Python
Classifier: Programming Language :: Python :: 3
Classifier: Programming Language :: Python :: 3 :: Only
Classifier: Programming Language :: Python :: 3.10
Classifier: Programming Language :: Python :: 3.11
Classifier: Programming Language :: Python :: 3.12
Classifier: Programming Language :: Python :: Implementation :: CPython
Classifier: Typing :: Typed
Requires-Python: >=3.10
License-File: LICENSE
Requires-Dist: python-mylog >=0.9.0
Requires-Dist: typing-extensions >=4.6.0
Requires-Dist: typer >=0.9.0
Requires-Dist: pydantic >=1.5
Requires-Dist: tomli ; python_version < "3.11"
